adytum
