Metadata-Version: 1.0
Name: Adytum-NetCIDR
Version: 0.0.1
Summary: Object representations, operations and logic for hosts, networks, and collections of networks.
Home-page: http://projects.adytum.us/tracs/NetCIDR
Author: Duncan McGreggor
Author-email: duncan@adytum.us
License: BSD
Platform: UNKNOWN
